setup.py
two_general_distributions/Binomialdistribution.py
two_general_distributions/Gaussiandistribution.py
two_general_distributions/Generaldistribution.py
two_general_distributions/__init__.py
two_general_distributions.egg-info/PKG-INFO
two_general_distributions.egg-info/SOURCES.txt
two_general_distributions.egg-info/dependency_links.txt
two_general_distributions.egg-info/not-zip-safe
two_general_distributions.egg-info/top_level.txt