Metadata-Version: 1.0
Name: two-general-distributions
Version: 0.1
Summary: Gaussian and Binomial distributions
Home-page: UNKNOWN
Author: Zhaoyun Ma
Author-email: mazhaoyunyh@gmail.com
License: UNKNOWN
Platform: UNKNOWN
